LICENSE
MANIFEST.in
README.md
setup.cfg
setup.py
oscookie/__init__.py
oscookie/database.py
oscookie/info.py
oscookie/logman.py
oscookie/maker.py
oscookie/utils.py
oscookie.egg-info/PKG-INFO
oscookie.egg-info/SOURCES.txt
oscookie.egg-info/dependency_links.txt
oscookie.egg-info/requires.txt
oscookie.egg-info/top_level.txt
oscookie/lists/alpine:3.1.txt
oscookie/lists/alpine:3.2.txt
oscookie/lists/alpine:3.3.txt
oscookie/lists/alpine:3.4.txt
oscookie/lists/alpine:3.5.txt
oscookie/lists/centos:5.txt
oscookie/lists/centos:6.txt
oscookie/lists/centos:7.txt
oscookie/lists/debian:8.6.txt
oscookie/lists/debian:sid.txt
oscookie/lists/debian:stretch.txt
oscookie/lists/fedora:22.txt
oscookie/lists/fedora:23.txt
oscookie/lists/fedora:24.txt
oscookie/lists/fedora:25.txt
oscookie/lists/mageia:5.txt
oscookie/lists/opensuse:13.2.txt
oscookie/lists/opensuse:42.1.txt
oscookie/lists/opensuse:42.2.txt
oscookie/lists/opensuse:tumbleweed.txt
oscookie/lists/oraclelinux:5.11.txt
oscookie/lists/oraclelinux:6.6.txt
oscookie/lists/oraclelinux:6.7.txt
oscookie/lists/oraclelinux:6.8.txt
oscookie/lists/oraclelinux:7.0.txt
oscookie/lists/oraclelinux:7.1.txt
oscookie/lists/oraclelinux:7.2.txt
oscookie/lists/oraclelinux:7.3.txt
oscookie/lists/photon:1.0.txt
oscookie/lists/pypi.txt
oscookie/lists/ubuntu:14.04.5.txt
oscookie/lists/ubuntu:16.04.txt
oscookie/lists/ubuntu:16.10.txt
oscookie/lists/ubuntu:17.04.txt